repositorytools/__init__.py
repositorytools/cli/__init__.py
repositorytools/cli/common.py
repositorytools/cli/commands/__init__.py
repositorytools/cli/commands/artifact.py
repositorytools/cli/commands/repo.py
repositorytools/lib/__init__.py
repositorytools/lib/artifact.py
repositorytools/lib/repository.py
repositorytools-4.2.5.dist-info/DESCRIPTION.rst
repositorytools-4.2.5.dist-info/METADATA
repositorytools-4.2.5.dist-info/RECORD
repositorytools-4.2.5.dist-info/WHEEL
repositorytools-4.2.5.dist-info/entry_points.txt
repositorytools-4.2.5.dist-info/metadata.json
repositorytools-4.2.5.dist-info/top_level.txt
tests/__init__.py
tests/cli/__init__.py
tests/cli/test_common.py
