Metadata-Version: 1.1
Name: repositorytools
Version: 4.2.5
Summary: Tools for working with artifact repositories
Home-page: https://github.com/stardust85/repositorytools
Author: Michel Samia
Author-email: stardust1985@gmail.com
License: Apache 2.0
Download-URL: https://github.com/stardust85/repositorytools/tarball/4.2.5
Platform: any
Classifier: Development Status :: 5 - Production/Stable
Classifier: Intended Audience :: Developers
Classifier: Intended Audience :: System Administrators
Classifier: Natural Language :: English
Classifier: License :: OSI Approved :: Apache Software License
Classifier: Programming Language :: Python
Classifier: Programming Language :: Python :: 2.6
Classifier: Programming Language :: Python :: 2.7
Classifier: Programming Language :: Python :: 3.3
Classifier: Programming Language :: Python :: 3.4
Classifier: Topic :: Software Development :: Libraries :: Python Modules
Classifier: Environment :: Console
